cbr_content/__init__.py
cbr_content/en/site/athena/athena-prompt.md
cbr_content/en/site/athena/banner.md
cbr_content/en/site/athena/index.md
cbr_content/en/site/athena/questions.toml
cbr_content/en/site/dev/index.md
cbr_content/en/site/dev/new-components/document-assistant.md
cbr_content/en/site/dev/testing/component-tester.md
cbr_content/en/site/docs/demos/index.md
cbr_content/en/site/docs/demos/personas/board-members/index.md
cbr_content/en/site/docs/demos/personas/cfo/budget-advisor-using-chat.md
cbr_content/en/site/docs/demos/personas/cfo/budget-advisor-using-forms.md
cbr_content/en/site/docs/demos/personas/cfo/index.md
cbr_content/en/site/docs/demos/personas/ciso/act-like-a-ciso.md
cbr_content/en/site/docs/demos/personas/ciso/ask-4x-same-model.md
cbr_content/en/site/docs/demos/personas/ciso/ciso-mindmap.md
cbr_content/en/site/docs/demos/personas/ciso/index.md
cbr_content/en/site/docs/demos/personas/ciso/speak-to-6x-types-of-cisos.md
cbr_content/en/site/docs/demos/personas/index.md
cbr_content/en/site/docs/demos/tools/github-helper.md
cbr_content/en/site/docs/demos/tools/index.md
cbr_content/en/site/docs/demos/tools/portuguese-journalist.md
cbr_content/en/site/docs/demos/tools/spelling-grammar-helper.md
cbr_content/en/site/docs/demos/use-cases/index.md
cbr_content/en/site/docs/demos/use-cases/owasp-projects.md
cbr_content/en/site/docs/demos/use-cases/simple-asm-and-binary-execution.md
cbr_content/en/site/docs/demos/use-cases/simple-asm-execution.md
cbr_content/en/site/docs/demos/use-cases/talk-with-ifconfig.md
cbr_content/en/site/docs/index.md
cbr_content/en/site/docs/platforms/groq/index.md
cbr_content/en/site/docs/platforms/groq/speak-in-6-languages.md
cbr_content/en/site/docs/platforms/groq/talk-with-3x-board-personas.md
cbr_content/en/site/docs/platforms/index.md
cbr_content/en/site/docs/platforms/mistral/index.md
cbr_content/en/site/docs/platforms/ollama/query-multiple-lllms.md
cbr_content/en/site/docs/platforms/open-router/index.md
cbr_content-0.9.78.dist-info/LICENSE
cbr_content-0.9.78.dist-info/METADATA
cbr_content-0.9.78.dist-info/WHEEL
cbr_content-0.9.78.dist-info/RECORD
