Metadata-Version: 2.3
Name: cbr_content
Version: 0.9.78
Summary: CBR - Content
License: MIT
Author: Dinis Cruz
Author-email: dinis.cruz@owasp.org
Requires-Python: >=3.11,<4.0
Classifier: License :: OSI Approved :: MIT License
Classifier: Programming Language :: Python :: 3
Classifier: Programming Language :: Python :: 3.11
Classifier: Programming Language :: Python :: 3.12
Classifier: Programming Language :: Python :: 3.13
Requires-Dist: osbot-markdown
Project-URL: Homepage, https://github.com/the-cyber-boardroom/cbr-content
Project-URL: Repository, https://github.com/the-cyber-boardroom/cbr-content
